voxterm/__init__.py
voxterm/__main__.py
voxterm/cli.py
voxterm/debug_api_key.py
voxterm/keyboard.py
voxterm/launcher.py
voxterm/logger.py
voxterm/menu.py
voxterm/modes.py
voxterm/run.py
voxterm/run_turn_based_fixed.py
voxterm/session_manager.py
voxterm/settings.py
voxterm/stream_protocol.py
voxterm/test_api_key.py
voxterm/test_minimal_connection.py
voxterm/test_turn_based.py
voxterm-0.0.3.dist-info/METADATA
voxterm-0.0.3.dist-info/WHEEL
voxterm-0.0.3.dist-info/entry_points.txt
voxterm-0.0.3.dist-info/top_level.txt
voxterm-0.0.3.dist-info/RECORD
